libname/__init__.py
libname/iss_track.py
isstrack_zilio-0.0.1.dist-info/METADATA
isstrack_zilio-0.0.1.dist-info/WHEEL
isstrack_zilio-0.0.1.dist-info/top_level.txt
isstrack_zilio-0.0.1.dist-info/RECORD
