Metadata-Version: 2.1
Name: isstrack-zilio
Version: 0.0.1
Summary: Real Time Track of ISS
Home-page: UNKNOWN
Author: Ziliotto Filippo
Author-email: filippo.ziliotto1996@gmail.com
License: UNKNOWN
Keywords: python,ISS,Tracking,Plotly,map
Platform: UNKNOWN
Classifier: Development Status :: 1 - Planning
Classifier: Intended Audience :: Developers
Classifier: Programming Language :: Python :: 3
Classifier: Operating System :: Unix
Classifier: Operating System :: MacOS :: MacOS X
Classifier: Operating System :: Microsoft :: Windows
Requires-Dist: plotly
Requires-Dist: pandas
